{
  "session_id": "session_20250909_211214",
  "timestamp": "2025-09-09T21:12:37.085959",
  "metadata": {
    "name": "session_0909_2112",
    "url": "https://www.baidu.com",
    "title": "百度一下，你就知道",
    "browser": "chromium",
    "viewport": {
      "width": 1920,
      "height": 1080
    }
  },
  "statistics": {
    "total_operations": 1,
    "total_screenshots": 1,
    "session_duration_seconds": 0.0,
    "pages_visited": [
      "https://www.baidu.com/"
    ]
  },
  "return_reference_element": null,
  "ai_analysis": {
    "analyzed": false,
    "analysis_timestamp": null,
    "suggested_parameters": [],
    "function_signature": null
  }
}